{
  "channel": {
    "display_name": "Christine Le",
    "channel_id": "UCvaslozYkHmrCU-vUaXZ9SQ",
    "youtube_title": "Christine Le",
    "group": "D_real_use",
    "subscriber_count": 343000
  },
  "videos": [
    {
      "video_id": "-GDSJF2E5Ng",
      "title": "STARTING LONG DISTANCE RUNNING. ONLY TO LOSE MY GLUTE GAINS #shorts",
      "description": "did my first marathon a few months ago, now we rebuild 😩\n\nFor more follow me on tiktok and instagram!\nhttps://www.instagram.com/christineleeee\nhttps://www.tiktok.com/@christineleeee?\n\n#running #workout #fitness",
      "thumbnail_url": "https://i.ytimg.com/vi/-GDSJF2E5Ng/maxresdefault.jpg",
      "view_count": 2222,
      "like_count": 13,
      "comment_count": 0,
      "duration": "0:08",
      "duration_secs": 8,
      "published_at": "2026-06-18T13:30:33Z",
      "channel_id": "UCvaslozYkHmrCU-vUaXZ9SQ",
      "channel_name": "Christine Le",
      "channel_youtube_title": "Christine Le",
      "channel_group": "D_real_use",
      "channel_subscriber_count": 343000,
      "video_url": "https://www.youtube.com/watch?v=-GDSJF2E5Ng",
      "engagement_rate": 0.59,
      "comment_rate": 0.0,
      "video_length_type": "Shorts",
      "content_tags": [
        "其他"
      ],
      "video_type": "其他",
      "brand_mentions": [],
      "hot_level": "",
      "view_to_sub_ratio": 0.65,
      "view_to_sub_tier": "频道冷启",
      "relevance_score": 20
    },
    {
      "video_id": "_iSmIG--Asc",
      "title": "WHEN YOU'RE THE DIGITAL CAMERA FRIEND #shorts",
      "description": "clocking in to help get all the instagram pics 😌\n\nFor more follow me on tiktok and instagram!\nhttps://www.instagram.com/christineleeee\nhttps://www.tiktok.com/@christineleeee?\n\n#digitalcamera #g7x #pinterestaesthetic #sonyalpha",
      "thumbnail_url": "https://i.ytimg.com/vi/_iSmIG--Asc/maxresdefault.jpg",
      "view_count": 3114,
      "like_count": 51,
      "comment_count": 0,
      "duration": "0:10",
      "duration_secs": 10,
      "published_at": "2026-06-17T13:30:29Z",
      "channel_id": "UCvaslozYkHmrCU-vUaXZ9SQ",
      "channel_name": "Christine Le",
      "channel_youtube_title": "Christine Le",
      "channel_group": "D_real_use",
      "channel_subscriber_count": 343000,
      "video_url": "https://www.youtube.com/watch?v=_iSmIG--Asc",
      "engagement_rate": 1.64,
      "comment_rate": 0.0,
      "video_length_type": "Shorts",
      "content_tags": [
        "其他"
      ],
      "video_type": "其他",
      "brand_mentions": [],
      "hot_level": "",
      "view_to_sub_ratio": 0.91,
      "view_to_sub_tier": "频道冷启",
      "relevance_score": 20
    },
    {
      "video_id": "b46X5M-86yQ",
      "title": "I HAVEN'T SHOPPED IN A WEEK #shorts",
      "description": "minor case of the shoppies\n\nFor more follow me on tiktok and instagram!\nhttps://www.instagram.com/christineleeee\nhttps://www.tiktok.com/@christineleeee?\n\n#gno #shopping #ootd",
      "thumbnail_url": "https://i.ytimg.com/vi/b46X5M-86yQ/maxresdefault.jpg",
      "view_count": 9596,
      "like_count": 160,
      "comment_count": 3,
      "duration": "0:07",
      "duration_secs": 7,
      "published_at": "2026-06-16T13:30:15Z",
      "channel_id": "UCvaslozYkHmrCU-vUaXZ9SQ",
      "channel_name": "Christine Le",
      "channel_youtube_title": "Christine Le",
      "channel_group": "D_real_use",
      "channel_subscriber_count": 343000,
      "video_url": "https://www.youtube.com/watch?v=b46X5M-86yQ",
      "engagement_rate": 1.7,
      "comment_rate": 0.031,
      "video_length_type": "Shorts",
      "content_tags": [
        "其他"
      ],
      "video_type": "其他",
      "brand_mentions": [],
      "hot_level": "",
      "view_to_sub_ratio": 2.8,
      "view_to_sub_tier": "频道一般",
      "relevance_score": 20
    },
    {
      "video_id": "EGCC_gJtL80",
      "title": "MY SONY A6400 CAMERA SETTINGS #shorts",
      "description": "my camera settings to mimic the look of the canon g7x 🤓\n\nFor more follow me on tiktok and instagram!\nhttps://www.instagram.com/christineleeee\nhttps://www.tiktok.com/@christineleeee?\n\n#camerasettings #flashcamera #photographytips #canong7x #sonyalpha",
      "thumbnail_url": "https://i.ytimg.com/vi/EGCC_gJtL80/maxresdefault.jpg",
      "view_count": 966,
      "like_count": 29,
      "comment_count": 0,
      "duration": "1:28",
      "duration_secs": 88,
      "published_at": "2026-06-15T13:30:00Z",
      "channel_id": "UCvaslozYkHmrCU-vUaXZ9SQ",
      "channel_name": "Christine Le",
      "channel_youtube_title": "Christine Le",
      "channel_group": "D_real_use",
      "channel_subscriber_count": 343000,
      "video_url": "https://www.youtube.com/watch?v=EGCC_gJtL80",
      "engagement_rate": 3.0,
      "comment_rate": 0.0,
      "video_length_type": "Short",
      "content_tags": [
        "其他"
      ],
      "video_type": "其他",
      "brand_mentions": [],
      "hot_level": "",
      "view_to_sub_ratio": 0.28,
      "view_to_sub_tier": "频道冷启",
      "relevance_score": 20
    },
    {
      "video_id": "DDgbYO5MS4g",
      "title": "MY MOST WORN HEELS THAT PASS THE 10K STEPS TEST #shorts",
      "description": "looking for some new comfy heels, please send recs! I’m willing to spend if I can walk miles in them 😩\n\nFor more follow me on tiktok and instagram!\nhttps://www.instagram.com/christineleeee\nhttps://www.tiktok.com/@christineleeee?\n\n#comfortableheels #nycfashion #bottega #heels #shoeinspo",
      "thumbnail_url": "https://i.ytimg.com/vi/DDgbYO5MS4g/maxresdefault.jpg",
      "view_count": 2916,
      "like_count": 129,
      "comment_count": 4,
      "duration": "1:44",
      "duration_secs": 104,
      "published_at": "2026-06-14T13:30:14Z",
      "channel_id": "UCvaslozYkHmrCU-vUaXZ9SQ",
      "channel_name": "Christine Le",
      "channel_youtube_title": "Christine Le",
      "channel_group": "D_real_use",
      "channel_subscriber_count": 343000,
      "video_url": "https://www.youtube.com/watch?v=DDgbYO5MS4g",
      "engagement_rate": 4.56,
      "comment_rate": 0.137,
      "video_length_type": "Short",
      "content_tags": [
        "其他"
      ],
      "video_type": "其他",
      "brand_mentions": [],
      "hot_level": "",
      "view_to_sub_ratio": 0.85,
      "view_to_sub_tier": "频道冷启",
      "relevance_score": 20
    },
    {
      "video_id": "IJgZr9EhMn8",
      "title": "COOL BUT CHIC #shorts",
      "description": "patiently waiting for spring in nyc… \n\nFor more follow me on tiktok and instagram!\nhttps://www.instagram.com/christineleeee\nhttps://www.tiktok.com/@christineleeee?\n\n#tomboy #outfitinspo #nycfashion #nyc #loafers",
      "thumbnail_url": "https://i.ytimg.com/vi/IJgZr9EhMn8/maxresdefault.jpg",
      "view_count": 3665,
      "like_count": 128,
      "comment_count": 1,
      "duration": "0:09",
      "duration_secs": 9,
      "published_at": "2026-06-13T13:30:16Z",
      "channel_id": "UCvaslozYkHmrCU-vUaXZ9SQ",
      "channel_name": "Christine Le",
      "channel_youtube_title": "Christine Le",
      "channel_group": "D_real_use",
      "channel_subscriber_count": 343000,
      "video_url": "https://www.youtube.com/watch?v=IJgZr9EhMn8",
      "engagement_rate": 3.52,
      "comment_rate": 0.027,
      "video_length_type": "Shorts",
      "content_tags": [
        "其他"
      ],
      "video_type": "其他",
      "brand_mentions": [],
      "hot_level": "",
      "view_to_sub_ratio": 1.07,
      "view_to_sub_tier": "频道一般",
      "relevance_score": 20
    },
    {
      "video_id": "fuYFYdziu84",
      "title": "WHERE ARE ALL THE HOT GIRLS GETTING THEIR GOING OUT HEELS #shorts",
      "description": "I can walk miles in my bottega heels but I’m looking for a different pair… \n\nFor more follow me on tiktok and instagram!\nhttps://www.instagram.com/christineleeee\nhttps://www.tiktok.com/@christineleeee?\n\n#comfortableheels #goingout #heels #outfitinspo #nycfashion",
      "thumbnail_url": "https://i.ytimg.com/vi/fuYFYdziu84/maxresdefault.jpg",
      "view_count": 7835,
      "like_count": 115,
      "comment_count": 5,
      "duration": "0:09",
      "duration_secs": 9,
      "published_at": "2026-06-12T13:30:12Z",
      "channel_id": "UCvaslozYkHmrCU-vUaXZ9SQ",
      "channel_name": "Christine Le",
      "channel_youtube_title": "Christine Le",
      "channel_group": "D_real_use",
      "channel_subscriber_count": 343000,
      "video_url": "https://www.youtube.com/watch?v=fuYFYdziu84",
      "engagement_rate": 1.53,
      "comment_rate": 0.064,
      "video_length_type": "Shorts",
      "content_tags": [
        "其他"
      ],
      "video_type": "其他",
      "brand_mentions": [],
      "hot_level": "",
      "view_to_sub_ratio": 2.28,
      "view_to_sub_tier": "频道一般",
      "relevance_score": 20
    },
    {
      "video_id": "Z4elZX2ygU4",
      "title": "JUST THINKING ABOUT WHEN MY HUSBAND USED MY RANDCO SLICK STICK... #shorts",
      "description": "“why is your deodorant stick so small” 🥲\n\nFor more follow me on tiktok and instagram!\nhttps://www.instagram.com/christineleeee\nhttps://www.tiktok.com/@christineleeee?\n\n#funny #couple #husband",
      "thumbnail_url": "https://i.ytimg.com/vi/Z4elZX2ygU4/maxresdefault.jpg",
      "view_count": 19732,
      "like_count": 67,
      "comment_count": 0,
      "duration": "0:08",
      "duration_secs": 8,
      "published_at": "2026-06-11T18:22:18Z",
      "channel_id": "UCvaslozYkHmrCU-vUaXZ9SQ",
      "channel_name": "Christine Le",
      "channel_youtube_title": "Christine Le",
      "channel_group": "D_real_use",
      "channel_subscriber_count": 343000,
      "video_url": "https://www.youtube.com/watch?v=Z4elZX2ygU4",
      "engagement_rate": 0.34,
      "comment_rate": 0.0,
      "video_length_type": "Shorts",
      "content_tags": [
        "其他"
      ],
      "video_type": "其他",
      "brand_mentions": [],
      "hot_level": "",
      "view_to_sub_ratio": 5.75,
      "view_to_sub_tier": "频道高分",
      "relevance_score": 20
    },
    {
      "video_id": "B-_mMOeWQWw",
      "title": "when he starts using a new shampoo but it's not one you've gotten him... #ad",
      "description": "His secret to getting compliments all day (and now mine!) @oldspice  #OldSpicePartner",
      "thumbnail_url": "https://i.ytimg.com/vi/B-_mMOeWQWw/maxresdefault.jpg",
      "view_count": 1906,
      "like_count": 33,
      "comment_count": 2,
      "duration": "0:43",
      "duration_secs": 43,
      "published_at": "2026-06-10T16:59:12Z",
      "channel_id": "UCvaslozYkHmrCU-vUaXZ9SQ",
      "channel_name": "Christine Le",
      "channel_youtube_title": "Christine Le",
      "channel_group": "D_real_use",
      "channel_subscriber_count": 343000,
      "video_url": "https://www.youtube.com/watch?v=B-_mMOeWQWw",
      "engagement_rate": 1.84,
      "comment_rate": 0.105,
      "video_length_type": "Shorts",
      "content_tags": [
        "其他"
      ],
      "video_type": "其他",
      "brand_mentions": [],
      "hot_level": "",
      "view_to_sub_ratio": 0.56,
      "view_to_sub_tier": "频道冷启",
      "relevance_score": 20
    },
    {
      "video_id": "ROp8Ecd6yz4",
      "title": "5 days in New York City: everywhere we ate and shopped 🍱🍸",
      "description": "After spending some relaxing time upstate, Brandon and I drove back to the city to catch up with friends and toured some apartments, for science of course... We hit our favorite vintage shops, flea markets, and new restaurants! The itinerary will be live on my Substack, but in the meantime, check out the other travel guides: https://christineleeee.substack.com/\n\n\n-- SHOP MY LIGHTROOM PRESETS --\n5 Presets for $15 https://www.christineleeee.com/lightroom-presets\n\nNEW VIDEO EVERY TUESDAY!!\nSUBSCRIB",
      "thumbnail_url": "https://i.ytimg.com/vi/ROp8Ecd6yz4/maxresdefault.jpg",
      "view_count": 46531,
      "like_count": 992,
      "comment_count": 24,
      "duration": "18:07",
      "duration_secs": 1087,
      "published_at": "2026-05-03T16:52:32Z",
      "channel_id": "UCvaslozYkHmrCU-vUaXZ9SQ",
      "channel_name": "Christine Le",
      "channel_youtube_title": "Christine Le",
      "channel_group": "D_real_use",
      "channel_subscriber_count": 343000,
      "video_url": "https://www.youtube.com/watch?v=ROp8Ecd6yz4",
      "engagement_rate": 2.18,
      "comment_rate": 0.052,
      "video_length_type": "Long",
      "content_tags": [
        "其他"
      ],
      "video_type": "其他",
      "brand_mentions": [],
      "hot_level": "",
      "view_to_sub_ratio": 13.57,
      "view_to_sub_tier": "频道爆款",
      "relevance_score": 20
    }
  ]
}